aes_module/__init__.py
aes_module/aes.py
aes_module/byte.py
aes_module/cipher.py
aes_module/operations.py
aes_module/state.py
aes_module/word.py
aes_package-0.2.dist-info/METADATA
aes_package-0.2.dist-info/WHEEL
aes_package-0.2.dist-info/top_level.txt
aes_package-0.2.dist-info/RECORD
