Metadata-Version: 2.1
Name: aes-package
Version: 0.2
Summary: A simple AES encryption and decryption module
Home-page: https://github.com/yourusername/aes_package
Author: Aryan Mahajan
Author-email: contact.aryan.mahajan@gmail.com
License: UNKNOWN
Platform: UNKNOWN
Classifier: Programming Language :: Python :: 3
Classifier: License :: OSI Approved :: MIT License
Classifier: Operating System :: OS Independent
Requires-Python: >=3.6
Provides-Extra: dev
Requires-Dist: pytest; extra == "dev"
